setup_commands.py
utils.py
django_fantasy/__init__.py
django_fantasy/apps.py
django_fantasy/models.py
django_fantasy/fixtures/fantasy-database.json
django_fantasy/migrations/0001_initial.py
django_fantasy/migrations/__init__.py
fantasy_database-2.0.3.post2.dist-info/DESCRIPTION.rst
fantasy_database-2.0.3.post2.dist-info/METADATA
fantasy_database-2.0.3.post2.dist-info/RECORD
fantasy_database-2.0.3.post2.dist-info/WHEEL
fantasy_database-2.0.3.post2.dist-info/metadata.json
fantasy_database-2.0.3.post2.dist-info/top_level.txt
